Organizasyon/Q3/data_mem.v
module data_mem(
    input  wire        clk,
    input  wire        MemWrite,
    input  wire [31:0] addr,
    input  wire [31:0] WriteData,
    output reg  [31:0] ReadData
);

    reg [31:0] mem [0:1023];

    // Asenkron okuma
    always @(*) begin
        ReadData = mem[addr[11:2]];
    end

    // Senkron yazma
    always @(posedge clk) begin
        if (MemWrite)
            mem[addr[11:2]] <= WriteData;
    end

endmodule

Organizasyon/Q3/alu.v
module alu(
    input  wire [31:0] A,
    input  wire [31:0] B,
    input  wire [2:0]  ALUControl,
    output reg  [31:0] ALUResult,
    output wire        Zero
);
    always @(*) begin
        case (ALUControl)
            3'b000: ALUResult = A + B;                // add
            3'b001: ALUResult = A - B;                // sub
            3'b100: ALUResult = A << B[4:0];          // sll  ← DÜZELTİLDİ
            3'b010: ALUResult = A & B;                // and
            3'b011: ALUResult = A | B;                // or
            3'b101: ALUResult = ($signed(A)<$signed(B)) ? 32'b1 : 32'b0; // slt
            default: ALUResult = 32'b0;
        endcase
    end

    assign Zero = (ALUResult == 0);

endmodule

Organizasyon/Q2/imm_gen.v
module imm_gen(
    input  wire [31:0] instr,
    input  wire [1:0]  ImmSrc,
    output reg  [31:0] ImmExt
);

    always @(*) begin
        case (ImmSrc)
            2'b00: // I-type
                ImmExt = {{20{instr[31]}}, instr[31:20]};
            2'b01: // S-type
                ImmExt = {{20{instr[31]}}, instr[31:25], instr[11:7]};
            2'b10: // B-type (beq)
                ImmExt = {{19{instr[31]}}, instr[31], instr[7],
                          instr[30:25], instr[11:8], 1'b0};
            2'b11: // J-type (jal)
                ImmExt = {{11{instr[31]}}, instr[31],
                          instr[19:12], instr[20],
                          instr[30:21], 1'b0};
            default:
                ImmExt = 32'b0;
        endcase
    end

endmodule

Organizasyon/Q1/regfile.v
module regfile(
    input  wire        clk,
    input  wire        RegWrite,
    input  wire [4:0]  rs1,
    input  wire [4:0]  rs2,
    input  wire [4:0]  rd,
    input  wire [31:0] WriteData,
    output wire [31:0] ReadData1,
    output wire [31:0] ReadData2
);

    reg [31:0] regs [0:31];
    integer i;
    initial for (i = 0; i < 32; i = i + 1) regs[i] = 0;

    assign ReadData1 = (rs1 != 0) ? regs[rs1] : 32'b0;
    assign ReadData2 = (rs2 != 0) ? regs[rs2] : 32'b0;

    always @(posedge clk) begin
        if (RegWrite && rd != 0)
            regs[rd] <= WriteData;
    end

endmodule

Organizasyon/Q1/instr_mem.v
module instr_mem(
    input  wire [31:0] addr,
    output reg  [31:0] instr
);

    // ROM  — instr.mem dosyasından okunur
    reg [31:0] mem [0:15];
    initial begin
        $readmemh("instr.mem", mem);
    end

    // adres >> 2 ile word-aligned index
    always @(*) begin
        instr = mem[addr[31:2]];
    end

endmodule

Organizasyon/Q2/datapath.v
module datapath(
    input  wire        clk,
    input  wire        rst,
    input  wire [6:0]  opcode,
    input  wire [2:0]  funct3,
    input  wire        funct7_5,
    input  wire        wr,
    input  wire [1:0]  ImmSrc,
    input  wire        ALUSrc,
    input  wire        MemWrite,
    input  wire [1:0]  ResultSrc,
    input  wire        Branch,
    input  wire [1:0]  ALUOp,
    input  wire        Jump,
    input  wire [2:0]  ALUControl,
    output wire [31:0] aluResult
);

    // Ara sinyaller
    wire [31:0] PC, PCPlus4, PCTarget, Instr;
    wire [31:0] RD1, RD2, ImmExt, ALUInB, MemRD, WBData;
    wire        Zero;

    // PC register
    reg [31:0] pc_reg;
    assign PC = pc_reg;
    always @(posedge clk or posedge rst) begin
        if (rst)                pc_reg <= 0;
        else if (Jump)          pc_reg <= PCTarget;
        else if (Branch && Zero) pc_reg <= PC + ImmExt;
        else                    pc_reg <= PCPlus4;
    end

    assign PCPlus4 = PC + 4;
    assign PCTarget = PC + ImmExt;

    // Instruction Fetch
    instr_mem IM(.addr(PC), .instr(Instr));

    // Register File
    regfile RF(
        .clk(clk), .RegWrite(wr),
        .rs1(Instr[19:15]), .rs2(Instr[24:20]), .rd(Instr[11:7]),
        .WriteData(WBData),
        .ReadData1(RD1), .ReadData2(RD2)
    );

    // Immediate Generation
    imm_gen IG(.instr(Instr), .ImmSrc(ImmSrc), .ImmExt(ImmExt));

    // ALU
    assign ALUInB = ALUSrc ? ImmExt : RD2;
    alu ALU_u(.A(RD1), .B(ALUInB),
              .ALUControl(ALUControl),
              .ALUResult(aluResult),
              .Zero(Zero));

    // Data Memory
    data_mem DM(.clk(clk), .MemWrite(MemWrite),
                .addr(aluResult), .WriteData(RD2),
                .ReadData(MemRD));

    // Write-back MUX
    assign WBData = (ResultSrc==2'b00) ? aluResult :
                    (ResultSrc==2'b01) ? MemRD :
                                         PCPlus4;

endmodule

Organizasyon/Q2/control.v
module control(
    input  wire [6:0]  opcode,
    input  wire [2:0]  funct3,
    input  wire        funct7_5,
    output reg         RegWrite,
    output reg  [1:0]  ImmSrc,
    output reg         ALUSrc,
    output reg         MemWrite,
    output reg  [1:0]  ResultSrc,
    output reg         Branch,
    output reg  [1:0]  ALUOp,
    output reg         Jump,
    output reg  [2:0]  ALUControl
);

    // Main Decoder
    always @(*) begin
        case (opcode)
            7'b0000011: begin // lw
                RegWrite=1; ImmSrc=2'b00; ALUSrc=1;
                MemWrite=0; ResultSrc=2'b01; Branch=0;
                ALUOp=2'b00; Jump=0;
            end
            7'b0100011: begin // sw
                RegWrite=0; ImmSrc=2'b01; ALUSrc=1;
                MemWrite=1; ResultSrc=2'b00; Branch=0;
                ALUOp=2'b00; Jump=0;
            end
            7'b0110011: begin // R-type
                RegWrite=1; ImmSrc=2'b00; ALUSrc=0;
                MemWrite=0; ResultSrc=2'b00; Branch=0;
                ALUOp=2'b10; Jump=0;
            end
            7'b1100011: begin // beq
                RegWrite=0; ImmSrc=2'b10; ALUSrc=0;
                MemWrite=0; ResultSrc=2'b00; Branch=1;
                ALUOp=2'b01; Jump=0;
            end
            7'b0010011: begin // addi, slti, ori, andi
                RegWrite=1; ImmSrc=2'b00; ALUSrc=1;
                MemWrite=0; ResultSrc=2'b00; Branch=0;
                ALUOp=2'b00; Jump=0;
            end
            7'b1101111: begin // jal
                RegWrite=1; ImmSrc=2'b11; ALUSrc=0;
                MemWrite=0; ResultSrc=2'b10; Branch=0;
                ALUOp=2'b00; Jump=1;
            end
            default: begin
                RegWrite=0; ImmSrc=2'b00; ALUSrc=0;
                MemWrite=0; ResultSrc=2'b00; Branch=0;
                ALUOp=2'b00; Jump=0;
            end
        endcase
    end

    // ALU Decoder
    always @(*) begin
        case (ALUOp)
            2'b00: begin
                if      (opcode==7'b0010011 && funct3==3'b010) ALUControl=3'b101; // slti
                else if (opcode==7'b0010011 && funct3==3'b110) ALUControl=3'b011; // ori
                else if (opcode==7'b0010011 && funct3==3'b111) ALUControl=3'b010; // andi
                else                                           ALUControl=3'b000; // add/addi
            end
            2'b01: ALUControl=3'b001; // sub (beq)
            2'b10: begin              // R-type
                case ({funct7_5,funct3})
                    4'b0000: ALUControl=3'b000; // add
                    4'b1000: ALUControl=3'b001; // sub
                    4'b0001: ALUControl=3'b100; // sll  ← DÜZELTİLDİ
                    4'b0010: ALUControl=3'b101; // slt
                    4'b0110: ALUControl=3'b011; // or
                    4'b0111: ALUControl=3'b010; // and
                    default: ALUControl=3'b000;
                endcase
            end
            default: ALUControl=3'b000;
        endcase
    end

endmodule

Organizasyon/Q2/tb_datapath_sll.v
`timescale 1ns/1ps
module tb_datapath_sll;
    reg         clk, rst;
    wire [6:0]  opcode;
    wire [2:0]  funct3;      // <<< bunlar Instr’den slice edilecek
    wire        funct7_5;
    wire        wr, ALUSrc, MemWrite, Branch, Jump;
    wire [1:0]  ImmSrc, ResultSrc, ALUOp;
    wire [2:0]  ALUControl;
    wire [31:0] aluResult;

    // 1) Control ve Datapath
    control CU (
        .opcode(opcode), .funct3(funct3), .funct7_5(funct7_5),
        .RegWrite(wr),  .ImmSrc(ImmSrc),  .ALUSrc(ALUSrc),
        .MemWrite(MemWrite), .ResultSrc(ResultSrc),
        .Branch(Branch), .ALUOp(ALUOp),  .Jump(Jump),
        .ALUControl(ALUControl)
    );
    datapath DP (
        .clk(clk), .rst(rst),
        .opcode(opcode), .funct3(funct3), .funct7_5(funct7_5),
        .wr(wr), .ImmSrc(ImmSrc), .ALUSrc(ALUSrc),
        .MemWrite(MemWrite), .ResultSrc(ResultSrc),
        .Branch(Branch), .ALUOp(ALUOp), .Jump(Jump),
        .ALUControl(ALUControl),
        .aluResult(aluResult)
    );

    // 2) Burada slice edin:
    assign opcode    = DP.Instr[6:0];
    assign funct3    = DP.Instr[14:12];  // ← 3 bit
    assign funct7_5  = DP.Instr[30];     // ← 1 bit

    // 3) Clock & Reset
    initial begin clk = 0; forever #5 clk = ~clk; end
    initial begin rst = 1; #10 rst = 0; end

    // 4) ROM’u yükle
    initial begin
        $readmemh("instr.mem", DP.IM.mem);
    end

    // 5) Dalga formu al
    initial begin
        $dumpfile("simulation_q2.vcd");
        $dumpvars(0, tb_datapath_sll);
    end

    // 6) Birkaç çevrim sonra bitir
    initial begin #100 $finish; end

endmodule

Organizasyon/Q2/simulation_q2.vcd
$date
	Thu May 01 22:45:26 2025
$end
$version
	Icarus Verilog
$end
$timescale
	1ps
$end
$scope module tb_datapath_sll $end
$var wire 1 ! wr $end
$var wire 7 " opcode [6:0] $end
$var wire 1 # funct7_5 $end
$var wire 3 $ funct3 [2:0] $end
$var wire 32 % aluResult [31:0] $end
$var wire 2 & ResultSrc [1:0] $end
$var wire 1 ' MemWrite $end
$var wire 1 ( Jump $end
$var wire 2 ) ImmSrc [1:0] $end
$var wire 1 * Branch $end
$var wire 1 + ALUSrc $end
$var wire 2 , ALUOp [1:0] $end
$var wire 3 - ALUControl [2:0] $end
$var reg 1 . clk $end
$var reg 1 / rst $end
$scope module CU $end
$var wire 7 0 opcode [6:0] $end
$var wire 1 # funct7_5 $end
$var wire 3 1 funct3 [2:0] $end
$var reg 3 2 ALUControl [2:0] $end
$var reg 2 3 ALUOp [1:0] $end
$var reg 1 + ALUSrc $end
$var reg 1 * Branch $end
$var reg 2 4 ImmSrc [1:0] $end
$var reg 1 ( Jump $end
$var reg 1 ' MemWrite $end
$var reg 1 ! RegWrite $end
$var reg 2 5 ResultSrc [1:0] $end
$upscope $end
$scope module DP $end
$var wire 3 6 ALUControl [2:0] $end
$var wire 2 7 ALUOp [1:0] $end
$var wire 1 + ALUSrc $end
$var wire 1 * Branch $end
$var wire 2 8 ImmSrc [1:0] $end
$var wire 1 ( Jump $end
$var wire 1 ' MemWrite $end
$var wire 2 9 ResultSrc [1:0] $end
$var wire 1 . clk $end
$var wire 1 / rst $end
$var wire 1 ! wr $end
$var wire 7 : opcode [6:0] $end
$var wire 1 # funct7_5 $end
$var wire 3 ; funct3 [2:0] $end
$var wire 32 < aluResult [31:0] $end
$var wire 1 = Zero $end
$var wire 32 > WBData [31:0] $end
$var wire 32 ? RD2 [31:0] $end
$var wire 32 @ RD1 [31:0] $end
$var wire 32 A PCTarget [31:0] $end
$var wire 32 B PCPlus4 [31:0] $end
$var wire 32 C PC [31:0] $end
$var wire 32 D MemRD [31:0] $end
$var wire 32 E Instr [31:0] $end
$var wire 32 F ImmExt [31:0] $end
$var wire 32 G ALUInB [31:0] $end
$var reg 32 H pc_reg [31:0] $end
$scope module ALU_u $end
$var wire 3 I ALUControl [2:0] $end
$var wire 32 J B [31:0] $end
$var wire 1 = Zero $end
$var wire 32 K A [31:0] $end
$var reg 32 L ALUResult [31:0] $end
$upscope $end
$scope module DM $end
$var wire 1 ' MemWrite $end
$var wire 32 M addr [31:0] $end
$var wire 1 . clk $end
$var wire 32 N WriteData [31:0] $end
$var reg 32 O ReadData [31:0] $end
$upscope $end
$scope module IG $end
$var wire 2 P ImmSrc [1:0] $end
$var wire 32 Q instr [31:0] $end
$var reg 32 R ImmExt [31:0] $end
$upscope $end
$scope module IM $end
$var wire 32 S addr [31:0] $end
$var reg 32 T instr [31:0] $end
$upscope $end
$scope module RF $end
$var wire 1 ! RegWrite $end
$var wire 32 U WriteData [31:0] $end
$var wire 1 . clk $end
$var wire 5 V rd [4:0] $end
$var wire 5 W rs1 [4:0] $end
$var wire 5 X rs2 [4:0] $end
$var wire 32 Y ReadData2 [31:0] $end
$var wire 32 Z ReadData1 [31:0] $end
$var integer 32 [ i [31:0] $end
$upscope $end
$upscope $end
$upscope $end
$enddefinitions $end
$comment Show the parameter values. $end
$dumpall
$end
#0
$dumpvars
b100000 [
b0 Z
b0 Y
b11 X
b0 W
b1 V
b11 U
b1100000000000010010011 T
b0 S
b11 R
b1100000000000010010011 Q
b0 P
bx O
b0 N
b11 M
b11 L
b0 K
b11 J
b0 I
b0 H
b11 G
b11 F
b1100000000000010010011 E
bx D
b0 C
b100 B
b11 A
b0 @
b0 ?
b11 >
0=
b11 <
b0 ;
b10011 :
b0 9
b0 8
b0 7
b0 6
b0 5
b0 4
b0 3
b0 2
b0 1
b10011 0
1/
0.
b0 -
b0 ,
1+
0*
b0 )
0(
0'
b0 &
b11 %
b0 $
0#
b10011 "
1!
$end
#5000
1.
#10000
0.
0/
#15000
b1 >
b1 U
b1 %
b1 <
b1 L
b1 M
b11 ?
b11 N
b11 Y
b1 G
b1 J
b10 V
b1 X
b1 F
b1 R
b100000000000100010011 E
b100000000000100010011 Q
b100000000000100010011 T
b1000 B
b101 A
b100 C
b100 H
b100 S
1.
#20000
0.
#25000
b110 >
b110 U
b110 %
b110 <
b110 L
b110 M
b100 -
b100 2
b100 6
b100 I
b10 ,
b10 3
b10 7
0+
b1 ?
b1 N
b1 Y
b11 @
b11 K
b11 Z
b1 G
b1 J
b1 $
b1 1
b1 ;
b110011 "
b110011 0
b110011 :
b11 V
b10 X
b1 W
b10 F
b10 R
b1000001001000110110011 E
b1000001001000110110011 Q
b1000001001000110110011 T
b1100 B
b1010 A
b1000 C
b1000 H
b1000 S
1.
#30000
0.
#35000
1=
b0 >
b0 U
b0 G
b0 J
b0 %
b0 <
b0 L
b0 M
b0 -
b0 2
b0 6
b0 I
b0 ,
b0 3
b0 7
0!
b0 ?
b0 N
b0 Y
b0 @
b0 K
b0 Z
b0 $
b0 1
b0 ;
b0 "
b0 0
b0 :
b0 V
b0 X
b0 W
b0 F
b0 R
b0 E
b0 Q
b0 T
b10000 B
b1100 A
b1100 C
b1100 H
b1100 S
1.
#40000
0.
#45000
b10100 B
b10000 A
b10000 C
b10000 H
b10000 S
1.
#50000
0.
#55000
b11000 B
b10100 A
b10100 C
b10100 H
b10100 S
1.
#60000
0.
#65000
b11100 B
b11000 A
b11000 C
b11000 H
b11000 S
1.
#70000
0.
#75000
b100000 B
b11100 A
b11100 C
b11100 H
b11100 S
1.
#80000
0.
#85000
b100100 B
b100000 A
b100000 C
b100000 H
b100000 S
1.
#90000
0.
#95000
b101000 B
b100100 A
b100100 C
b100100 H
b100100 S
1.
