Organizasyon/Q3/data_mem.v
module data_mem(
    input  wire        clk,
    input  wire        MemWrite,
    input  wire [31:0] addr,
    input  wire [31:0] WriteData,
    output reg  [31:0] ReadData
);

    reg [31:0] mem [0:1023];

    // Asenkron okuma
    always @(*) begin
        ReadData = mem[addr[11:2]];
    end

    // Senkron yazma
    always @(posedge clk) begin
        if (MemWrite)
            mem[addr[11:2]] <= WriteData;
    end

endmodule

Organizasyon/Q1/alu.v
module alu(
    input  wire [31:0] A,
    input  wire [31:0] B,
    input  wire [2:0]  ALUControl,
    output reg  [31:0] ALUResult,
    output wire        Zero
);

    always @(*) begin
        case (ALUControl)
            3'b000: ALUResult = A + B;        // add
            3'b001: ALUResult = A - B;        // sub
            3'b010: ALUResult = A & B;        // and
            3'b011: ALUResult = A | B;        // or
            3'b101: ALUResult = ($signed(A) < $signed(B)) ? 32'b1 : 32'b0; // slt
            default: ALUResult = 32'b0;
        endcase
    end

    assign Zero = (ALUResult == 0);

endmodule

Organizasyon/Q2/imm_gen.v
module imm_gen(
    input  wire [31:0] instr,
    input  wire [1:0]  ImmSrc,
    output reg  [31:0] ImmExt
);

    always @(*) begin
        case (ImmSrc)
            2'b00: // I-type
                ImmExt = {{20{instr[31]}}, instr[31:20]};
            2'b01: // S-type
                ImmExt = {{20{instr[31]}}, instr[31:25], instr[11:7]};
            2'b10: // B-type (beq)
                ImmExt = {{19{instr[31]}}, instr[31], instr[7],
                          instr[30:25], instr[11:8], 1'b0};
            2'b11: // J-type (jal)
                ImmExt = {{11{instr[31]}}, instr[31],
                          instr[19:12], instr[20],
                          instr[30:21], 1'b0};
            default:
                ImmExt = 32'b0;
        endcase
    end

endmodule

Organizasyon/Q1/regfile.v
module regfile(
    input  wire        clk,
    input  wire        RegWrite,
    input  wire [4:0]  rs1,
    input  wire [4:0]  rs2,
    input  wire [4:0]  rd,
    input  wire [31:0] WriteData,
    output wire [31:0] ReadData1,
    output wire [31:0] ReadData2
);

    reg [31:0] regs [0:31];
    integer i;
    initial for (i = 0; i < 32; i = i + 1) regs[i] = 0;

    assign ReadData1 = (rs1 != 0) ? regs[rs1] : 32'b0;
    assign ReadData2 = (rs2 != 0) ? regs[rs2] : 32'b0;

    always @(posedge clk) begin
        if (RegWrite && rd != 0)
            regs[rd] <= WriteData;
    end

endmodule

Organizasyon/Q1/instr_mem.v
module instr_mem(
    input  wire [31:0] addr,
    output reg  [31:0] instr
);

    // ROM  — instr.mem dosyasından okunur
    reg [31:0] mem [0:15];
    initial begin
        $readmemh("instr.mem", mem);
    end

    // adres >> 2 ile word-aligned index
    always @(*) begin
        instr = mem[addr[31:2]];
    end

endmodule

Organizasyon/Q2/datapath.v
module datapath(
    input  wire        clk,
    input  wire        rst,
    input  wire [6:0]  opcode,
    input  wire [2:0]  funct3,
    input  wire        funct7_5,
    input  wire        wr,
    input  wire [1:0]  ImmSrc,
    input  wire        ALUSrc,
    input  wire        MemWrite,
    input  wire [1:0]  ResultSrc,
    input  wire        Branch,
    input  wire [1:0]  ALUOp,
    input  wire        Jump,
    input  wire [2:0]  ALUControl,
    output wire [31:0] aluResult
);

    // Ara sinyaller
    wire [31:0] PC, PCPlus4, PCTarget, Instr;
    wire [31:0] RD1, RD2, ImmExt, ALUInB, MemRD, WBData;
    wire        Zero;

    // PC register
    reg [31:0] pc_reg;
    assign PC = pc_reg;
    always @(posedge clk or posedge rst) begin
        if (rst)                pc_reg <= 0;
        else if (Jump)          pc_reg <= PCTarget;
        else if (Branch && Zero) pc_reg <= PC + ImmExt;
        else                    pc_reg <= PCPlus4;
    end

    assign PCPlus4 = PC + 4;
    assign PCTarget = PC + ImmExt;

    // Instruction Fetch
    instr_mem IM(.addr(PC), .instr(Instr));

    // Register File
    regfile RF(
        .clk(clk), .RegWrite(wr),
        .rs1(Instr[19:15]), .rs2(Instr[24:20]), .rd(Instr[11:7]),
        .WriteData(WBData),
        .ReadData1(RD1), .ReadData2(RD2)
    );

    // Immediate Generation
    imm_gen IG(.instr(Instr), .ImmSrc(ImmSrc), .ImmExt(ImmExt));

    // ALU
    assign ALUInB = ALUSrc ? ImmExt : RD2;
    alu ALU_u(.A(RD1), .B(ALUInB),
              .ALUControl(ALUControl),
              .ALUResult(aluResult),
              .Zero(Zero));

    // Data Memory
    data_mem DM(.clk(clk), .MemWrite(MemWrite),
                .addr(aluResult), .WriteData(RD2),
                .ReadData(MemRD));

    // Write-back MUX
    assign WBData = (ResultSrc==2'b00) ? aluResult :
                    (ResultSrc==2'b01) ? MemRD :
                                         PCPlus4;

endmodule

Organizasyon/Q1/control.v
module control(
    input  wire [6:0]  opcode,
    input  wire [2:0]  funct3,
    input  wire        funct7_5,
    output reg         RegWrite,
    output reg  [1:0]  ImmSrc,
    output reg         ALUSrc,
    output reg         MemWrite,
    output reg  [1:0]  ResultSrc,
    output reg         Branch,
    output reg  [1:0]  ALUOp,
    output reg         Jump,
    output reg  [2:0]  ALUControl
);

    always @(*) begin
        case (opcode)
            7'b0000011: begin // lw
                RegWrite=1; ImmSrc=2'b00; ALUSrc=1;
                MemWrite=0; ResultSrc=2'b01; Branch=0;
                ALUOp=2'b00; Jump=0;
            end
            7'b0100011: begin // sw
                RegWrite=0; ImmSrc=2'b01; ALUSrc=1;
                MemWrite=1; ResultSrc=2'b00; Branch=0;
                ALUOp=2'b00; Jump=0;
            end
            7'b0110011: begin // R-type
                RegWrite=1; ImmSrc=2'b00; ALUSrc=0;
                MemWrite=0; ResultSrc=2'b00; Branch=0;
                ALUOp=2'b10; Jump=0;
            end
            7'b1100011: begin // beq
                RegWrite=0; ImmSrc=2'b10; ALUSrc=0;
                MemWrite=0; ResultSrc=2'b00; Branch=1;
                ALUOp=2'b01; Jump=0;
            end
            7'b0010011: begin // I-type ALU (addi, slti, ori, andi)
                RegWrite=1; ImmSrc=2'b00; ALUSrc=1;
                MemWrite=0; ResultSrc=2'b00; Branch=0;
                ALUOp=2'b00; Jump=0;
            end
            7'b1101111: begin // jal
                RegWrite=1; ImmSrc=2'b11; ALUSrc=0;
                MemWrite=0; ResultSrc=2'b10; Branch=0;
                ALUOp=2'b00; Jump=1;
            end
            default: begin
                RegWrite=0; ImmSrc=2'b00; ALUSrc=0;
                MemWrite=0; ResultSrc=2'b00; Branch=0;
                ALUOp=2'b00; Jump=0;
            end
        endcase
    end

    // ALU Decoder
    always @(*) begin
        case (ALUOp)
            2'b00: // I-type ALU or add for lw/sw
                ALUControl = (opcode==7'b0010011 && funct3==3'b010) ? 3'b101 : // slti
                             (opcode==7'b0010011 && funct3==3'b110) ? 3'b011 : // ori
                             (opcode==7'b0010011 && funct3==3'b111) ? 3'b010 : // andi
                                                                              3'b000; // add/addi
            2'b01: ALUControl = 3'b001; // sub (beq)
            2'b10: begin               // R-type
                case ({funct7_5, funct3})
                    4'b0000: ALUControl = 3'b000; // add
                    4'b1000: ALUControl = 3'b001; // sub
                    4'b0010: ALUControl = 3'b101; // slt
                    4'b0110: ALUControl = 3'b011; // or
                    4'b0111: ALUControl = 3'b010; // and
                    default: ALUControl = 3'b000;
                endcase
            end
            default: ALUControl = 3'b000;
        endcase
    end

endmodule

Organizasyon/Q1/tb_datapath.v
`timescale 1ns/1ps
module tb_datapath;
    reg         clk, rst;
    wire [6:0]  opcode;
    wire [2:0]  funct3;
    wire        funct7_5;
    wire        wr, ALUSrc, MemWrite, Branch, Jump;
    wire [1:0]  ImmSrc, ResultSrc, ALUOp;
    wire [2:0]  ALUControl;
    wire [31:0] aluResult;

    // DUT: Control
    control CU (
        .opcode(opcode), .funct3(funct3), .funct7_5(funct7_5),
        .RegWrite(wr), .ImmSrc(ImmSrc), .ALUSrc(ALUSrc),
        .MemWrite(MemWrite), .ResultSrc(ResultSrc),
        .Branch(Branch), .ALUOp(ALUOp), .Jump(Jump),
        .ALUControl(ALUControl)
    );

    // DUT: Datapath
    datapath DP (
        .clk(clk), .rst(rst),
        .opcode(opcode), .funct3(funct3), .funct7_5(funct7_5),
        .wr(wr), .ImmSrc(ImmSrc), .ALUSrc(ALUSrc),
        .MemWrite(MemWrite), .ResultSrc(ResultSrc),
        .Branch(Branch), .ALUOp(ALUOp), .Jump(Jump),
        .ALUControl(ALUControl),
        .aluResult(aluResult)
    );

    // Instr’in bit alanları
    assign opcode   = DP.Instr[6:0];
    assign funct3   = DP.Instr[14:12];
    assign funct7_5 = DP.Instr[30];

    // Clock & Reset
    initial begin
        clk = 0; forever #5 clk = ~clk;
    end
    initial begin
        rst = 1; #10 rst = 0;
    end

    // VCD dump
    initial begin
        $dumpfile("simulation_q1.vcd");
        $dumpvars(0, tb_datapath);
    end

    // Sadece adres sınırı: 12 talimat ⇒ 12*4 = 48 zamanı biraz aşalım
    initial begin
        #1000 $finish;
    end

endmodule

Organizasyon/Q1/simulation_q1.vcd
$date
	Thu May 01 19:56:45 2025
$end
$version
	Icarus Verilog
$end
$timescale
	1ps
$end
$scope module tb_datapath $end
$var wire 1 ! wr $end
$var wire 7 " opcode [6:0] $end
$var wire 1 # funct7_5 $end
$var wire 3 $ funct3 [2:0] $end
$var wire 32 % aluResult [31:0] $end
$var wire 2 & ResultSrc [1:0] $end
$var wire 1 ' MemWrite $end
$var wire 1 ( Jump $end
$var wire 2 ) ImmSrc [1:0] $end
$var wire 1 * Branch $end
$var wire 1 + ALUSrc $end
$var wire 2 , ALUOp [1:0] $end
$var wire 3 - ALUControl [2:0] $end
$var reg 1 . clk $end
$var reg 1 / rst $end
$scope module CU $end
$var wire 7 0 opcode [6:0] $end
$var wire 1 # funct7_5 $end
$var wire 3 1 funct3 [2:0] $end
$var reg 3 2 ALUControl [2:0] $end
$var reg 2 3 ALUOp [1:0] $end
$var reg 1 + ALUSrc $end
$var reg 1 * Branch $end
$var reg 2 4 ImmSrc [1:0] $end
$var reg 1 ( Jump $end
$var reg 1 ' MemWrite $end
$var reg 1 ! RegWrite $end
$var reg 2 5 ResultSrc [1:0] $end
$upscope $end
$scope module DP $end
$var wire 3 6 ALUControl [2:0] $end
$var wire 2 7 ALUOp [1:0] $end
$var wire 1 + ALUSrc $end
$var wire 1 * Branch $end
$var wire 2 8 ImmSrc [1:0] $end
$var wire 1 ( Jump $end
$var wire 1 ' MemWrite $end
$var wire 2 9 ResultSrc [1:0] $end
$var wire 1 . clk $end
$var wire 1 / rst $end
$var wire 1 ! wr $end
$var wire 7 : opcode [6:0] $end
$var wire 1 # funct7_5 $end
$var wire 3 ; funct3 [2:0] $end
$var wire 32 < aluResult [31:0] $end
$var wire 1 = Zero $end
$var wire 32 > WBData [31:0] $end
$var wire 32 ? RD2 [31:0] $end
$var wire 32 @ RD1 [31:0] $end
$var wire 32 A PCTarget [31:0] $end
$var wire 32 B PCPlus4 [31:0] $end
$var wire 32 C PC [31:0] $end
$var wire 32 D MemRD [31:0] $end
$var wire 32 E Instr [31:0] $end
$var wire 32 F ImmExt [31:0] $end
$var wire 32 G ALUInB [31:0] $end
$var reg 32 H pc_reg [31:0] $end
$scope module ALU_u $end
$var wire 3 I ALUControl [2:0] $end
$var wire 32 J B [31:0] $end
$var wire 1 = Zero $end
$var wire 32 K A [31:0] $end
$var reg 32 L ALUResult [31:0] $end
$upscope $end
$scope module DM $end
$var wire 1 ' MemWrite $end
$var wire 32 M addr [31:0] $end
$var wire 1 . clk $end
$var wire 32 N WriteData [31:0] $end
$var reg 32 O ReadData [31:0] $end
$upscope $end
$scope module IG $end
$var wire 2 P ImmSrc [1:0] $end
$var wire 32 Q instr [31:0] $end
$var reg 32 R ImmExt [31:0] $end
$upscope $end
$scope module IM $end
$var wire 32 S addr [31:0] $end
$var reg 32 T instr [31:0] $end
$upscope $end
$scope module RF $end
$var wire 1 ! RegWrite $end
$var wire 32 U WriteData [31:0] $end
$var wire 1 . clk $end
$var wire 5 V rd [4:0] $end
$var wire 5 W rs1 [4:0] $end
$var wire 5 X rs2 [4:0] $end
$var wire 32 Y ReadData2 [31:0] $end
$var wire 32 Z ReadData1 [31:0] $end
$var integer 32 [ i [31:0] $end
$upscope $end
$upscope $end
$upscope $end
$enddefinitions $end
$comment Show the parameter values. $end
$dumpall
$end
#0
$dumpvars
b100000 [
b0 Z
b0 Y
b1010 X
b0 W
b1 V
b1010 U
b101000000000000010010011 T
b0 S
b1010 R
b101000000000000010010011 Q
b0 P
bx O
b0 N
b1010 M
b1010 L
b0 K
b1010 J
b0 I
b0 H
b1010 G
b1010 F
b101000000000000010010011 E
bx D
b0 C
b100 B
b1010 A
b0 @
b0 ?
b1010 >
0=
b1010 <
b0 ;
b10011 :
b0 9
b0 8
b0 7
b0 6
b0 5
b0 4
b0 3
b0 2
b0 1
b10011 0
1/
0.
b0 -
b0 ,
1+
0*
b0 )
0(
0'
b0 &
b1010 %
b0 $
0#
b10011 "
1!
$end
#5000
1.
#10000
0.
0/
#15000
b10100 >
b10100 U
b10100 %
b10100 <
b10100 L
b10100 M
b10 ,
b10 3
b10 7
0+
b1010 ?
b1010 N
b1010 Y
b1010 @
b1010 K
b1010 Z
b1010 G
b1010 J
b110011 "
b110011 0
b110011 :
b10 V
b1 X
b1 W
b1 F
b1 R
b100001000000100110011 E
b100001000000100110011 Q
b100001000000100110011 T
b1000 B
b101 A
b100 C
b100 H
b100 S
1.
#20000
0.
#25000
b1010 >
b1010 U
b1010 %
b1010 <
b1010 L
b1010 M
b1 -
b1 2
b1 6
b1 I
b10100 @
b10100 K
b10100 Z
1#
b11 V
b10 W
b10000000001 F
b10000000001 R
b1000000000100010000000110110011 E
b1000000000100010000000110110011 Q
b1000000000100010000000110110011 T
b1100 B
b10000001001 A
b1000 C
b1000 H
b1000 S
1.
#30000
0.
#35000
b1 >
b1 U
b10100 G
b10100 J
b1 %
b1 <
b1 L
b1 M
b101 -
b101 2
b101 6
b101 I
b10100 ?
b10100 N
b10100 Y
b0 @
b0 K
b0 Z
0#
b10 $
b10 1
b10 ;
b100 V
b10 X
b0 W
b10 F
b10 R
b1000000010001000110011 E
b1000000010001000110011 Q
b1000000010001000110011 T
b10000 B
b1110 A
b1100 C
b1100 H
b1100 S
1.
#40000
0.
#45000
b0 >
b0 U
1=
b0 %
b0 <
b0 L
b0 M
b10 -
b10 2
b10 6
b10 I
b1010 @
b1010 K
b1010 Z
b111 $
b111 1
b111 ;
b101 V
b1 W
b1000001111001010110011 E
b1000001111001010110011 Q
b1000001111001010110011 T
b10100 B
b10010 A
b10000 C
b10000 H
b10000 S
1.
#50000
0.
#55000
b11110 >
b11110 U
0=
b11110 %
b11110 <
b11110 L
b11110 M
b11 -
b11 2
b11 6
b11 I
b110 $
b110 1
b110 ;
b110 V
b1000001110001100110011 E
b1000001110001100110011 Q
b1000001110001100110011 T
b11000 B
b10110 A
b10100 C
b10100 H
b10100 S
1.
#60000
0.
#65000
b0 >
b0 U
1=
b0 %
b0 <
b0 L
b0 M
b101 G
b101 J
b101 -
b101 2
b101 6
b101 I
b0 ,
b0 3
b0 7
1+
b0 ?
b0 N
b0 Y
b10 $
b10 1
b10 ;
b10011 "
b10011 0
b10011 :
b111 V
b101 X
b101 F
b101 R
b10100001010001110010011 E
b10100001010001110010011 Q
b10100001010001110010011 T
b11100 B
b11101 A
b11000 C
b11000 H
b11000 S
1.
#70000
0.
#75000
b1011 >
b1011 U
0=
b1011 %
b1011 <
b1011 L
b1011 M
b11 -
b11 2
b11 6
b11 I
b1010 ?
b1010 N
b1010 Y
b11 G
b11 J
b110 $
b110 1
b110 ;
b1000 V
b11 X
b11 F
b11 R
b1100001110010000010011 E
b1100001110010000010011 Q
b1100001110010000010011 T
b100000 B
b11111 A
b11100 C
b11100 H
b11100 S
1.
#80000
0.
#85000
b10 >
b10 U
b10 %
b10 <
b10 L
b10 M
b10 -
b10 2
b10 6
b10 I
b0 ?
b0 N
b0 Y
b111 G
b111 J
b111 $
b111 1
b111 ;
b1001 V
b111 X
b111 F
b111 R
b11100001111010010010011 E
b11100001111010010010011 Q
b11100001111010010010011 T
b100100 B
b100111 A
b100000 C
b100000 H
b100000 S
1.
#90000
0.
#95000
b0 >
b0 U
1=
b0 %
b0 <
b0 L
b0 M
b0 -
b0 2
b0 6
b0 I
1'
b1 )
b1 4
b1 8
b1 P
0!
b10100 ?
b10100 N
b10100 Y
b0 @
b0 K
b0 Z
b0 G
b0 J
b10 $
b10 1
b10 ;
b100011 "
b100011 0
b100011 :
b0 V
b10 X
b0 W
b0 F
b0 R
b1000000010000000100011 E
b1000000010000000100011 Q
b1000000010000000100011 T
b101000 B
b100100 A
b100100 C
b100100 H
b100100 S
1.
#100000
0.
#105000
b10100 >
b10100 U
1=
b0 %
b0 <
b0 L
b0 M
b1 &
b1 5
b1 9
0'
b0 )
b0 4
b0 8
b0 P
1!
b0 ?
b0 N
b0 Y
b0 G
b0 J
b11 "
b11 0
b11 :
b1010 V
b0 X
b0 F
b0 R
b10100 D
b10100 O
b10010100000011 E
b10010100000011 Q
b10010100000011 T
b101100 B
b101000 A
b101000 C
b101000 H
b101000 S
1.
#110000
0.
#115000
b10100 D
b10100 O
b0 >
b0 U
1=
b0 %
b0 <
b0 L
b0 M
b1 -
b1 2
b1 6
b1 I
b1 ,
b1 3
b1 7
1*
b0 &
b0 5
b0 9
0+
b10 )
b10 4
b10 8
b10 P
0!
b10100 ?
b10100 N
b10100 Y
b10100 @
b10100 K
b10100 Z
b10100 G
b10100 J
b0 $
b0 1
b0 ;
b1100011 "
b1100011 0
b1100011 :
b100 V
b10 X
b1010 W
b100 F
b100 R
b1001010000001001100011 E
b1001010000001001100011 Q
b1001010000001001100011 T
b110000 B
b110000 A
b101100 C
b101100 H
b101100 S
1.
#120000
0.
#125000
bx D
bx O
b110100 >
b110100 U
b1011 G
b1011 J
0=
b1011 %
b1011 <
b1011 L
b1011 M
b0 -
b0 2
b0 6
b0 I
1(
b0 ,
b0 3
b0 7
0*
b10 &
b10 5
b10 9
b11 )
b11 4
b11 8
b11 P
1!
b1011 ?
b1011 N
b1011 Y
b0 @
b0 K
b0 Z
b1101111 "
b1101111 0
b1101111 :
b1100 V
b1000 X
b0 W
b1000 F
b1000 R
b100000000000011001101111 E
b100000000000011001101111 Q
b100000000000011001101111 T
b110100 B
b111000 A
b110000 C
b110000 H
b110000 S
1.
#130000
0.
#135000
b10100 D
b10100 O
1=
b0 %
b0 <
b0 L
b0 M
b0 G
b0 J
0(
b0 &
b0 5
b0 9
b0 )
b0 4
b0 8
b0 P
0!
b0 ?
b0 N
b0 Y
b0 >
b0 U
b0 "
b0 0
b0 :
b0 V
b0 X
b0 F
b0 R
b0 E
b0 Q
b0 T
b111100 B
b111000 A
b111000 C
b111000 H
b111000 S
1.
#140000
0.
#145000
b1000000 B
b111100 A
b111100 C
b111100 H
b111100 S
1.
#150000
0.
#155000
bx G
bx J
bx -
bx 2
bx 6
bx I
bx ?
bx N
bx Y
bx @
bx K
bx Z
x#
bx $
bx 1
bx ;
bx "
bx 0
bx :
bx V
bx X
bx W
bx F
bx R
bx E
bx Q
bx T
b1000100 B
bx A
b1000000 C
b1000000 H
b1000000 S
1.
#160000
0.
#165000
b1001000 B
b1000100 C
b1000100 H
b1000100 S
1.
#170000
0.
#175000
b1001100 B
b1001000 C
b1001000 H
b1001000 S
1.
#180000
0.
#185000
b1010000 B
b1001100 C
b1001100 H
b1001100 S
1.
#190000
0.
#195000
b1010100 B
b1010000 C
b1010000 H
b1010000 S
1.
#200000
0.
#205000
b1011000 B
b1010100 C
b1010100 H
b1010100 S
1.
#210000
0.
#215000
b1011100 B
b1011000 C
b1011000 H
b1011000 S
1.
#220000
0.
#225000
b1100000 B
b1011100 C
b1011100 H
b1011100 S
1.
#230000
0.
#235000
b1100100 B
b1100000 C
b1100000 H
b1100000 S
1.
#240000
0.
#245000
b1101000 B
b1100100 C
b1100100 H
b1100100 S
1.
#250000
0.
#255000
b1101100 B
b1101000 C
b1101000 H
b1101000 S
1.
#260000
0.
#265000
b1110000 B
b1101100 C
b1101100 H
b1101100 S
1.
#270000
0.
#275000
b1110100 B
b1110000 C
b1110000 H
b1110000 S
1.
#280000
0.
#285000
b1111000 B
b1110100 C
b1110100 H
b1110100 S
1.
#290000
0.
#295000
b1111100 B
b1111000 C
b1111000 H
b1111000 S
1.
#300000
0.
#305000
b10000000 B
b1111100 C
b1111100 H
b1111100 S
1.
#310000
0.
#315000
b10000100 B
b10000000 C
b10000000 H
b10000000 S
1.
#320000
0.
#325000
b10001000 B
b10000100 C
b10000100 H
b10000100 S
1.
#330000
0.
#335000
b10001100 B
b10001000 C
b10001000 H
b10001000 S
1.
#340000
0.
#345000
b10010000 B
b10001100 C
b10001100 H
b10001100 S
1.
#350000
0.
#355000
b10010100 B
b10010000 C
b10010000 H
b10010000 S
1.
#360000
0.
#365000
b10011000 B
b10010100 C
b10010100 H
b10010100 S
1.
#370000
0.
#375000
b10011100 B
b10011000 C
b10011000 H
b10011000 S
1.
#380000
0.
#385000
b10100000 B
b10011100 C
b10011100 H
b10011100 S
1.
#390000
0.
#395000
b10100100 B
b10100000 C
b10100000 H
b10100000 S
1.
#400000
0.
#405000
b10101000 B
b10100100 C
b10100100 H
b10100100 S
1.
#410000
0.
#415000
b10101100 B
b10101000 C
b10101000 H
b10101000 S
1.
#420000
0.
#425000
b10110000 B
b10101100 C
b10101100 H
b10101100 S
1.
#430000
0.
#435000
b10110100 B
b10110000 C
b10110000 H
b10110000 S
1.
#440000
0.
#445000
b10111000 B
b10110100 C
b10110100 H
b10110100 S
1.
#450000
0.
#455000
b10111100 B
b10111000 C
b10111000 H
b10111000 S
1.
#460000
0.
#465000
b11000000 B
b10111100 C
b10111100 H
b10111100 S
1.
#470000
0.
#475000
b11000100 B
b11000000 C
b11000000 H
b11000000 S
1.
#480000
0.
#485000
b11001000 B
b11000100 C
b11000100 H
b11000100 S
1.
#490000
0.
#495000
b11001100 B
b11001000 C
b11001000 H
b11001000 S
1.
#500000
0.
#505000
b11010000 B
b11001100 C
b11001100 H
b11001100 S
1.
#510000
0.
#515000
b11010100 B
b11010000 C
b11010000 H
b11010000 S
1.
#520000
0.
#525000
b11011000 B
b11010100 C
b11010100 H
b11010100 S
1.
#530000
0.
#535000
b11011100 B
b11011000 C
b11011000 H
b11011000 S
1.
#540000
0.
#545000
b11100000 B
b11011100 C
b11011100 H
b11011100 S
1.
#550000
0.
#555000
b11100100 B
b11100000 C
b11100000 H
b11100000 S
1.
#560000
0.
#565000
b11101000 B
b11100100 C
b11100100 H
b11100100 S
1.
#570000
0.
#575000
b11101100 B
b11101000 C
b11101000 H
b11101000 S
1.
#580000
0.
#585000
b11110000 B
b11101100 C
b11101100 H
b11101100 S
1.
#590000
0.
#595000
b11110100 B
b11110000 C
b11110000 H
b11110000 S
1.
#600000
0.
#605000
b11111000 B
b11110100 C
b11110100 H
b11110100 S
1.
#610000
0.
#615000
b11111100 B
b11111000 C
b11111000 H
b11111000 S
1.
#620000
0.
#625000
b100000000 B
b11111100 C
b11111100 H
b11111100 S
1.
#630000
0.
#635000
b100000100 B
b100000000 C
b100000000 H
b100000000 S
1.
#640000
0.
#645000
b100001000 B
b100000100 C
b100000100 H
b100000100 S
1.
#650000
0.
#655000
b100001100 B
b100001000 C
b100001000 H
b100001000 S
1.
#660000
0.
#665000
b100010000 B
b100001100 C
b100001100 H
b100001100 S
1.
#670000
0.
#675000
b100010100 B
b100010000 C
b100010000 H
b100010000 S
1.
#680000
0.
#685000
b100011000 B
b100010100 C
b100010100 H
b100010100 S
1.
#690000
0.
#695000
b100011100 B
b100011000 C
b100011000 H
b100011000 S
1.
#700000
0.
#705000
b100100000 B
b100011100 C
b100011100 H
b100011100 S
1.
#710000
0.
#715000
b100100100 B
b100100000 C
b100100000 H
b100100000 S
1.
#720000
0.
#725000
b100101000 B
b100100100 C
b100100100 H
b100100100 S
1.
#730000
0.
#735000
b100101100 B
b100101000 C
b100101000 H
b100101000 S
1.
#740000
0.
#745000
b100110000 B
b100101100 C
b100101100 H
b100101100 S
1.
#750000
0.
#755000
b100110100 B
b100110000 C
b100110000 H
b100110000 S
1.
#760000
0.
#765000
b100111000 B
b100110100 C
b100110100 H
b100110100 S
1.
#770000
0.
#775000
b100111100 B
b100111000 C
b100111000 H
b100111000 S
1.
#780000
0.
#785000
b101000000 B
b100111100 C
b100111100 H
b100111100 S
1.
#790000
0.
#795000
b101000100 B
b101000000 C
b101000000 H
b101000000 S
1.
#800000
0.
#805000
b101001000 B
b101000100 C
b101000100 H
b101000100 S
1.
#810000
0.
#815000
b101001100 B
b101001000 C
b101001000 H
b101001000 S
1.
#820000
0.
#825000
b101010000 B
b101001100 C
b101001100 H
b101001100 S
1.
#830000
0.
#835000
b101010100 B
b101010000 C
b101010000 H
b101010000 S
1.
#840000
0.
#845000
b101011000 B
b101010100 C
b101010100 H
b101010100 S
1.
#850000
0.
#855000
b101011100 B
b101011000 C
b101011000 H
b101011000 S
1.
#860000
0.
#865000
b101100000 B
b101011100 C
b101011100 H
b101011100 S
1.
#870000
0.
#875000
b101100100 B
b101100000 C
b101100000 H
b101100000 S
1.
#880000
0.
#885000
b101101000 B
b101100100 C
b101100100 H
b101100100 S
1.
#890000
0.
#895000
b101101100 B
b101101000 C
b101101000 H
b101101000 S
1.
#900000
0.
#905000
b101110000 B
b101101100 C
b101101100 H
b101101100 S
1.
#910000
0.
#915000
b101110100 B
b101110000 C
b101110000 H
b101110000 S
1.
#920000
0.
#925000
b101111000 B
b101110100 C
b101110100 H
b101110100 S
1.
#930000
0.
#935000
b101111100 B
b101111000 C
b101111000 H
b101111000 S
1.
#940000
0.
#945000
b110000000 B
b101111100 C
b101111100 H
b101111100 S
1.
#950000
0.
#955000
b110000100 B
b110000000 C
b110000000 H
b110000000 S
1.
#960000
0.
#965000
b110001000 B
b110000100 C
b110000100 H
b110000100 S
1.
#970000
0.
#975000
b110001100 B
b110001000 C
b110001000 H
b110001000 S
1.
#980000
0.
#985000
b110010000 B
b110001100 C
b110001100 H
b110001100 S
1.
#990000
0.
#995000
b110010100 B
b110010000 C
b110010000 H
b110010000 S
1.
